igorCA.py
igorControl.py
igorServlet.py
igorSetup.py
igorVar.py
igor/__init__.py
igor/__main__.py
igor/_version.py
igor/actions.py
igor/besthostname.py
igor/callUrl.py
igor/debugEchoCommand.py
igor/mimetypematch.py
igor/myLogger.py
igor/pluginHandler.py
igor/rwlock.py
igor/sseListener.py
igor/webApp.py
igor/xmlDatabase.py
igor/access/__init__.py
igor/access/capability.py
igor/access/checker.py
igor/access/consistency.py
igor/access/dummyAccess.py
igor/access/issuer.py
igor/access/vars.py
igor/bootScripts/initscript-igor
igor/bootScripts/nl.cwi.dis.igor.plist
igor/igorDatabase.empty/.DS_Store
igor/igorDatabase.empty/database.xml
igor/igorDatabase.empty/shadow.xml
igor/igorDatabase.empty/ca/.DS_Store
igor/igorDatabase.empty/ca/intermediate/crlnumber
igor/igorDatabase.empty/ca/intermediate/index.txt
igor/igorDatabase.empty/ca/intermediate/openssl.cnf.in
igor/igorDatabase.empty/ca/intermediate/readme.txt
igor/igorDatabase.empty/ca/intermediate/serial
igor/igorDatabase.empty/ca/intermediate/certs/readme.txt
igor/igorDatabase.empty/ca/intermediate/crl/readme.txt
igor/igorDatabase.empty/ca/intermediate/csr/readme.txt
igor/igorDatabase.empty/ca/intermediate/newcerts/readme.txt
igor/igorDatabase.empty/ca/intermediate/private/readme.txt
igor/igorDatabase.empty/ca/root/crlnumber
igor/igorDatabase.empty/ca/root/index.txt
igor/igorDatabase.empty/ca/root/openssl.cnf.in
igor/igorDatabase.empty/ca/root/readme.txt
igor/igorDatabase.empty/ca/root/serial
igor/igorDatabase.empty/ca/root/certs/readme.txt
igor/igorDatabase.empty/ca/root/crl/readme.txt
igor/igorDatabase.empty/ca/root/newcerts/readme.txt
igor/igorDatabase.empty/ca/root/private/readme.txt
igor/igorDatabase.empty/plugins/readme.txt
igor/igorDatabase.empty/scripts/readme.txt
igor/igorDatabase.empty/static/readme.txt
igor/plugins/__init__.py
igor/plugins/__init__.pyc
igor/plugins/__pycache__/__init__.cpython-37.pyc
igor/scripts/debugEchoScript
igor/static/apple-touch-icon.png
igor/static/favicon.ico
igor_iot-0.99.1.dist-info/LICENSE.txt
igor_iot-0.99.1.dist-info/METADATA
igor_iot-0.99.1.dist-info/WHEEL
igor_iot-0.99.1.dist-info/entry_points.txt
igor_iot-0.99.1.dist-info/top_level.txt
igor_iot-0.99.1.dist-info/RECORD
