Metadata-Version: 2.1
Name: igor-iot
Version: 0.99.1
Summary: REST-like IoT server
Home-page: https://github.com/cwi-dis/igor
Author: Jack Jansen
Author-email: Jack.Jansen@cwi.nl
License: MIT
Project-URL: Documentation, https://igor-iot.readthedocs.io
Project-URL: Issue tracker, https://github.com/cwi-dis/igor/issues
Platform: UNKNOWN
Classifier: Development Status :: 4 - Beta
Classifier: Framework :: Flask
Classifier: Intended Audience :: End Users/Desktop
Classifier: Topic :: Database
Classifier: Topic :: Home Automation
Classifier: License :: OSI Approved :: MIT License
Classifier: Programming Language :: Python :: 2.7
Classifier: Programming Language :: Python :: 3
Requires-Dist: future
Requires-Dist: httplib2
Requires-Dist: requests
Requires-Dist: flask
Requires-Dist: gevent
Requires-Dist: python-dateutil
Requires-Dist: py-dom-xpath-six
Requires-Dist: passlib
Requires-Dist: pyjwt
Requires-Dist: pyopenssl
Requires-Dist: markdown
